lenskit_hpf/__init__.py
lenskit_hpf/_pt.py
lenskit_hpf/hpf.py
lenskit_hpf-0.14.0.dist-info/LICENSE.md
lenskit_hpf-0.14.0.dist-info/WHEEL
lenskit_hpf-0.14.0.dist-info/METADATA
lenskit_hpf-0.14.0.dist-info/RECORD
