Metadata-Version: 2.1
Name: lenskit-hpf
Version: 0.14.0
Summary: Hierarchical Poisson factorization for LensKit.
Author-email: Michael Ekstrand <michaelekstrand@boisestate.edu>
Requires-Python: >= 3.7
Classifier: License :: OSI Approved :: MIT License
Classifier: Programming Language :: Python :: 3
Classifier: Programming Language :: Python :: 3.7
Classifier: Programming Language :: Python :: 3.8
Classifier: Programming Language :: Python :: 3.9
Classifier: Programming Language :: Python :: 3.10
Classifier: Operating System :: OS Independent
Classifier: Intended Audience :: Science/Research
Requires-Dist: lenskit==0.14.*
Requires-Dist: hpfrec==0.2.*
Requires-Dist: flit >= 3 ; extra == "dev"
Requires-Dist: packaging >= 20 ; extra == "dev"
Requires-Dist: flake8 >= 3 ; extra == "dev"
Requires-Dist: coverage >= 5 ; extra == "dev"
Requires-Dist: pytest-cov >= 2.12 ; extra == "dev"
Requires-Dist: lenskit[doc] ; extra == "doc"
Requires-Dist: pytest >= 6 ; extra == "test"
Requires-Dist: pytest-doctestplus >= 0.9 ; extra == "test"
Project-URL: GitHub, https://github.com/lenskit/lenskit-hpf
Project-URL: homepage, https://lkpy.lenskit.org/projects/lenskit-hpf
Provides-Extra: dev
Provides-Extra: doc
Provides-Extra: test
